delete_me_discord/__init__.py
delete_me_discord/api.py
delete_me_discord/cleaner.py
delete_me_discord/discovery.py
delete_me_discord/options.py
delete_me_discord/type_enums.py
delete_me_discord/utils.py
delete_me_discord-1.4.0.dist-info/licenses/LICENSE
test/test_parse_time_delta.py
delete_me_discord-1.4.0.dist-info/METADATA
delete_me_discord-1.4.0.dist-info/WHEEL
delete_me_discord-1.4.0.dist-info/entry_points.txt
delete_me_discord-1.4.0.dist-info/top_level.txt
delete_me_discord-1.4.0.dist-info/RECORD
