Metadata-Version: 2.4
Name: delete-me-discord
Version: 1.4.0
Summary: Tool to mass delete your Discord messages and reactions with filters and retention controls.
Author-email: "Jan T. Müller" <mail@jantmueller.com>
License: MIT
Project-URL: homepage, https://github.com/janthmueller/delete-me-discord
Project-URL: documentation, https://janthmueller.github.io/delete-me-discord/
Project-URL: source, https://github.com/janthmueller/delete-me-discord
Project-URL: tracker, https://github.com/janthmueller/delete-me-discord/issues
Classifier: Intended Audience :: Developers
Classifier: Topic :: Communications :: Chat
Classifier: License :: OSI Approved :: MIT License
Classifier: Operating System :: OS Independent
Classifier: Programming Language :: Python :: 3
Classifier: Programming Language :: Python :: 3.7
Classifier: Programming Language :: Python :: 3.8
Classifier: Programming Language :: Python :: 3.9
Classifier: Programming Language :: Python :: 3.10
Classifier: Programming Language :: Python :: 3.11
Requires-Python: >=3.7
License-File: LICENSE
Requires-Dist: requests>=2.0.0
Requires-Dist: rich<14,>=13
Dynamic: license-file
